loginflow/__init__.py
loginflow/_core.py
loginflow/demo.py
loginflow/email.py
loginflow/errors.py
loginflow-0.0.1.dist-info/LICENSE
loginflow-0.0.1.dist-info/METADATA
loginflow-0.0.1.dist-info/WHEEL
loginflow-0.0.1.dist-info/top_level.txt
loginflow-0.0.1.dist-info/RECORD
